README.rst
setup.py
bespin/__init__.py
bespin/actions.py
bespin/collector.py
bespin/errors.py
bespin/executor.py
bespin/formatter.py
bespin/helpers.py
bespin/layers.py
bespin/processes.py
bespin/task_finder.py
bespin/tasks.py
bespin.egg-info/PKG-INFO
bespin.egg-info/SOURCES.txt
bespin.egg-info/dependency_links.txt
bespin.egg-info/entry_points.txt
bespin.egg-info/requires.txt
bespin.egg-info/top_level.txt
bespin/amazon/__init__.py
bespin/amazon/cloudformation.py
bespin/amazon/cloudformation_yaml.py
bespin/amazon/credentials.py
bespin/amazon/ec2.py
bespin/amazon/kms.py
bespin/amazon/mixin.py
bespin/amazon/s3.py
bespin/amazon/sqs.py
bespin/operations/__init__.py
bespin/operations/builder.py
bespin/operations/deployer.py
bespin/operations/downtimer.py
bespin/operations/plan.py
bespin/operations/ssh.py
bespin/option_spec/__init__.py
bespin/option_spec/artifact_objs.py
bespin/option_spec/bespin_obj.py
bespin/option_spec/bespin_specs.py
bespin/option_spec/deployment_check.py
bespin/option_spec/imports.py
bespin/option_spec/netscaler.py
bespin/option_spec/stack_objs.py
bespin/option_spec/stack_specs.py
bespin/option_spec/task_objs.py